moons1d/__init__.py
moons1d/catalogue.py
moons1d/interface.py
moons1d/simulator.py
moons1d/spectra.py
moons1d/utils.py
moons1d/models/Instrument/MOONS_mode.ini
moons1d/models/Instrument/QE_4RG.txt
moons1d/models/Instrument/QE_LBNL.txt
moons1d/models/Instrument/QE_RI.txt
moons1d/models/Instrument/QE_nearIR.txt
moons1d/models/Instrument/telescope_eff.txt
moons1d/models/Instrument/throughput_H_best.txt
moons1d/models/Instrument/throughput_H_worst.txt
moons1d/models/Instrument/throughput_RI_best.txt
moons1d/models/Instrument/throughput_RI_worst.txt
moons1d/models/Instrument/throughput_YJ_best.txt
moons1d/models/Instrument/throughput_YJ_worst.txt
moons1d/models/Skymodel/SkyTemplate_ESO_a1.0.fits
moons1d/models/Skymodel/SkyTemplate_ESO_a1.2.fits
moons1d/models/Skymodel/SkyTemplate_ESO_a1.4.fits
moons1d/models/Skymodel/SkyTemplate_ESO_a1.6.fits
moons1d/models/Skymodel/SkyTemplate_ESO_a1.8.fits
moons1d/models/Skymodel/SkyTemplate_ESO_a2.0.fits
moons1d-1.0.3.dist-info/LICENSE
moons1d-1.0.3.dist-info/METADATA
moons1d-1.0.3.dist-info/WHEEL
moons1d-1.0.3.dist-info/top_level.txt
moons1d-1.0.3.dist-info/RECORD
