Metadata-Version: 2.1
Name: moons1d
Version: 1.0.3
Summary: 1D simulator for MOONS/VLT
Home-page: https://gitlab.obspm.fr/mrodrigues/moons1d
Author: Myriam Rodrigues
Author-email: myriam.rodrigues@obspm.fr
License: MIT
License-File: LICENSE
Requires-Dist: numpy (>=1.16)
Requires-Dist: astropy (==4.3.1)
Requires-Dist: configobj
Requires-Dist: matplotlib
Requires-Dist: pyparsing
Requires-Dist: scipy
Requires-Dist: numpy
Requires-Dist: synphot
Requires-Dist: spectres
